PythonMeta/__init__.py
PythonMeta/core.py
PythonMeta-1.26.dist-info/LICENSE
PythonMeta-1.26.dist-info/METADATA
PythonMeta-1.26.dist-info/WHEEL
PythonMeta-1.26.dist-info/top_level.txt
PythonMeta-1.26.dist-info/RECORD
