Metadata-Version: 2.1
Name: PythonMeta
Version: 1.26
Summary: A Python module of Meta-Analysis, usually applied in systemtic reviews of Evidence-based Medicine.
Home-page: http://www.pymeta.com
Author: 邓宏勇 Deng, Hongyong
Author-email: dephew@126.com
License: UNKNOWN
Keywords: meta analysis,meta-analysis,meta_analysis,systematic review,EBM,Evidence-based Medicine
Platform: UNKNOWN
Classifier: Programming Language :: Python :: 3
Classifier: License :: OSI Approved :: GNU General Public License v3 (GPLv3)
Classifier: Operating System :: OS Independent
Classifier: Topic :: Scientific/Engineering :: Bio-Informatics
Classifier: Topic :: Scientific/Engineering :: Information Analysis
Classifier: Topic :: Scientific/Engineering :: Medical Science Apps.
Requires-Python: >=3.5
License-File: LICENSE
Requires-Dist: matplotlib
Requires-Dist: statsmodels
